noraise/__init__.py
noraise/noraise.py
noraise-0.0.16.dist-info/LICENSE
noraise-0.0.16.dist-info/METADATA
noraise-0.0.16.dist-info/WHEEL
noraise-0.0.16.dist-info/top_level.txt
noraise-0.0.16.dist-info/RECORD
